setup.py
tests/__init__.py
tests/conftest.py
tests/test_db.py
tests/test_storage.py
threedb/__init__.py
threedb/config.py
threedb/filter.py
threedb/storage.py
threedb/utils.py
threedb.egg-info/PKG-INFO
threedb.egg-info/SOURCES.txt
threedb.egg-info/dependency_links.txt
threedb.egg-info/requires.txt
threedb.egg-info/top_level.txt