Metadata-Version: 1.0
Name: threedb
Version: 1.1
Summary: ThreeDB is a lightweight database optimized for data storage used testing
Home-page: https://github.com/EvgenyAK/3db
Author: Kurochkin Evgeny
Author-email: UNKNOWN
License: UNKNOWN
Keywords: ddt testing testdata
Platform: UNKNOWN
